kalamari/__init__.py
kalamari/main.py
kalamari/commands/__init__.py
kalamari/commands/test.py
utils/__init__.py
utils/api_call.py
utils/list_files.py
kalamari_cli-1.10.10.dist-info/METADATA
kalamari_cli-1.10.10.dist-info/WHEEL
kalamari_cli-1.10.10.dist-info/entry_points.txt
kalamari_cli-1.10.10.dist-info/top_level.txt
kalamari_cli-1.10.10.dist-info/RECORD
