Metadata-Version: 2.1
Name: kalamari-cli
Version: 1.10.10
Summary: Kalamari CLI tool for smart contract management and development.
Author: Sentou Technologies
Author-email: hello@sentou.tech
Requires-Dist: argparse
Requires-Dist: requests
